splunkr/__init__.py
splunkr/splunk_http_event_collector.py
splunkr-0.0.9.dist-info/METADATA
splunkr-0.0.9.dist-info/WHEEL
splunkr-0.0.9.dist-info/top_level.txt
splunkr-0.0.9.dist-info/RECORD
